{
	"Shots":{
		"T367":{ // 367 Missile Launcher Lv.1
			"Delay":8,
			"Sound":7,
			"Trail":6,
			"Pieces":[
				{"Sprite":31,"AttackPower":{"Shrapnel":"MissileShrapnelLow"},"AccelY":1}
			]
		},
		"T368":{ // 368 Missile Launcher Lv.2
			"Delay":9,
			"Sound":7,
			"Trail":6,
			"PiecesPerFire":2,
			"Pieces":[
				{"Sprite":31,"AttackPower":{"Shrapnel":"MissileShrapnelLow"},"MoveX":1,"MoveY":-1,"AccelY":1},
				{"Sprite":31,"AttackPower":{"Shrapnel":"MissileShrapnelLow"},"MoveX":-1,"MoveY":-1,"AccelY":1}
			]
		},
		"T369":{ // 369 Missile Launcher Lv.3
			"Delay":10,
			"Sound":7,
			"Trail":6,
			"PiecesPerFire":3,
			"Pieces":[
				{"Sprite":31,"AttackPower":{"Shrapnel":"MissileShrapnelLow"},"MoveX":1,"MoveY":-1,"AccelY":1},
				{"Sprite":31,"AttackPower":{"Shrapnel":"MissileShrapnelLow"},"MoveX":-1,"MoveY":-1,"AccelY":1},
				{"Sprite":31,"AttackPower":{"Shrapnel":"MissileShrapnelLow"},"AccelY":1}
			]
		},
		"T370":{ // 370 Missile Launcher Lv.4
			"Delay":11,
			"Sound":7,
			"Trail":6,
			"PiecesPerFire":4,
			"Pieces":[
				{"Sprite":31,"AttackPower":{"Shrapnel":"MissileShrapnelLow"},"MoveX":1,"MoveY":-2,"AccelY":1},
				{"Sprite":31,"AttackPower":{"Shrapnel":"MissileShrapnelLow"},"MoveX":-1,"MoveY":-2,"AccelY":1},
				{"Sprite":31,"AttackPower":{"Shrapnel":"MissileShrapnelLow"},"X":-3,"AccelY":1},
				{"Sprite":31,"AttackPower":{"Shrapnel":"MissileShrapnelLow"},"X":3,"AccelY":1}
			]
		},
		"T371":{ // 371 Missile Launcher Lv.5
			"Delay":12,
			"Sound":7,
			"Trail":6,
			"Pieces":[
				{"Sprite":32,"AttackPower":{"Shrapnel":"PhoenixShrapnelB"},"MoveY":-2,"AccelY":1}
			]
		},
		"T372":{ // 372 Missile Launcher Lv.6
			"Delay":12,
			"Sound":7,
			"Trail":6,
			"PiecesPerFire":2,
			"Pieces":[
				{"Sprite":31,"AttackPower":{"Shrapnel":"MissileShrapnelLow"},"MoveX":-1,"MoveY":-3,"AccelY":1},
				{"Sprite":32,"AttackPower":{"Shrapnel":"PhoenixShrapnelB"},"MoveY":-2,"AccelY":1},
				{"Sprite":31,"AttackPower":{"Shrapnel":"MissileShrapnelLow"},"MoveX":1,"MoveY":-3,"AccelY":1},
				{"Sprite":32,"AttackPower":{"Shrapnel":"PhoenixShrapnelB"},"MoveY":-2,"AccelY":1}
			]
		},
		"T373":{ // 373 Missile Launcher Lv.7
			"Delay":12,
			"Sound":7,
			"Trail":6,
			"PiecesPerFire":3,
			"Pieces":[
				{"Sprite":31,"AttackPower":{"Shrapnel":"MissileShrapnelLow"},"MoveX":-1,"MoveY":-3,"AccelY":1},
				{"Sprite":32,"AttackPower":{"Shrapnel":"PhoenixShrapnelB"},"MoveY":-2,"AccelY":1},
				{"Sprite":31,"AttackPower":{"Shrapnel":"MissileShrapnelLow"},"MoveX":1,"MoveY":-3,"AccelY":1}
			]
		},
		"T374":{ // 374 Missile Launcher Lv.8
			"Delay":12,
			"Sound":7,
			"Trail":6,
			"PiecesPerFire":3,
			"Pieces":[
				{"Sprite":31,"AttackPower":{"Shrapnel":"MissileShrapnelLow"},"MoveX":-1,"MoveY":-4,"AccelY":1},
				{"Sprite":32,"AttackPower":{"Shrapnel":"MissileShrapnelHigh"},"MoveY":-3,"AccelY":1},
				{"Sprite":31,"AttackPower":{"Shrapnel":"MissileShrapnelLow"},"MoveX":1,"MoveY":-4,"AccelY":1}
			]
		},
		"T375":{ // 375 Missile Launcher Lv.9
			"Delay":12,
			"Sound":7,
			"Trail":6,
			"PiecesPerFire":2,
			"Pieces":[
				{"Sprite":32,"AttackPower":{"Shrapnel":"MissileShrapnelHigh"},"X":-6,"MoveY":-4,"AccelY":1},
				{"Sprite":32,"AttackPower":{"Shrapnel":"MissileShrapnelHigh"},"X":6,"MoveY":-4,"AccelY":1}
			]
		},
		"T376":{ // 376 Missile Launcher Lv.10
			"Delay":12,
			"Sound":7,
			"Trail":6,
			"PiecesPerFire":4,
			"Pieces":[
				{"Sprite":32,"AttackPower":{"Shrapnel":"MissileShrapnelHigh"},"X":-6,"MoveY":-4,"AccelY":1},
				{"Sprite":32,"AttackPower":{"Shrapnel":"MissileShrapnelHigh"},"X":6,"MoveY":-4,"AccelY":1},
				{"Sprite":31,"AttackPower":{"Shrapnel":"MissileShrapnelLow"},"MoveX":1,"MoveY":-1,"AccelY":1},
				{"Sprite":31,"AttackPower":{"Shrapnel":"MissileShrapnelLow"},"MoveX":-1,"MoveY":-1,"AccelY":1}
			]
		},
		"T377":{ // 377 Missile Launcher Lv.11
			"Delay":12,
			"Sound":7,
			"Trail":6,
			"PiecesPerFire":3,
			"Pieces":[
				{"Sprite":33,"AttackPower":{"Shrapnel":"MissileShrapnelMega"},"MoveY":-4,"AccelY":1},
				{"Sprite":31,"AttackPower":{"Shrapnel":"MissileShrapnelLow"},"MoveX":1,"MoveY":-1,"AccelY":1},
				{"Sprite":31,"AttackPower":{"Shrapnel":"MissileShrapnelLow"},"MoveX":-1,"MoveY":-1,"AccelY":1}
			]
		}
	},
	"Ports":{
		"P17":{ // 17 [U-Ship ~ E]
			"Name":"Light Missile Launcher",
			"NormalShots":["T367","T368","T369","T370","T371","T372","T373","T374","T375","T376","T377"]
		}
	}
}